setup.py
kinuppquantlib/__init__.py
kinuppquantlib/quant_lib.py
kinuppquantlib.egg-info/PKG-INFO
kinuppquantlib.egg-info/SOURCES.txt
kinuppquantlib.egg-info/dependency_links.txt
kinuppquantlib.egg-info/not-zip-safe
kinuppquantlib.egg-info/top_level.txt