Metadata-Version: 2.1
Name: kinuppquantlib
Version: 0.1
Summary: A quantitative library for stock market analysis.
Author: Caio Kinupp
Author-email: ckinupp@gmail.com
